apns.py
sipyapns-1.0.0.data/scripts/apns-send
sipyapns-1.0.0.dist-info/DESCRIPTION.rst
sipyapns-1.0.0.dist-info/METADATA
sipyapns-1.0.0.dist-info/RECORD
sipyapns-1.0.0.dist-info/WHEEL
sipyapns-1.0.0.dist-info/metadata.json
sipyapns-1.0.0.dist-info/top_level.txt
