Metadata-Version: 2.0
Name: sipyapns
Version: 1.0.0
Summary: A python library for interacting with the Apple Push Notification Service
Home-page: UNKNOWN
Author: KyoungMook Ryu
Author-email: kyoungmook.ryu@nrise.net
License: unlicense.org
Download-URL: https://github.com/nrise/SIPyAPNs
Platform: UNKNOWN
